PyGui/__init__.py
PyGui/widgets.py
pyguix-0.1.1.dist-info/LICENSE
pyguix-0.1.1.dist-info/METADATA
pyguix-0.1.1.dist-info/WHEEL
pyguix-0.1.1.dist-info/top_level.txt
pyguix-0.1.1.dist-info/RECORD
