Metadata-Version: 2.1
Name: pyguix
Version: 0.1.1
Summary: GUI Library using Pygame
Home-page: https://github.com/iTecAI/PyGui
Author: iTecX
Author-email: matteovh@gmail.com
License: UNKNOWN
Platform: UNKNOWN
Classifier: Programming Language :: Python :: 3
Classifier: License :: OSI Approved :: MIT License
Classifier: Operating System :: OS Independent
Requires-Dist: pygame
